odoo/addons/endpoint_jsonifier/README.rst
odoo/addons/endpoint_jsonifier/__init__.py
odoo/addons/endpoint_jsonifier/__manifest__.py
odoo/addons/endpoint_jsonifier/i18n/endpoint_jsonifier.pot
odoo/addons/endpoint_jsonifier/i18n/it.po
odoo/addons/endpoint_jsonifier/models/__init__.py
odoo/addons/endpoint_jsonifier/models/endpoint_mixin.py
odoo/addons/endpoint_jsonifier/readme/CONTRIBUTORS.md
odoo/addons/endpoint_jsonifier/readme/DESCRIPTION.md
odoo/addons/endpoint_jsonifier/readme/USAGE.md
odoo/addons/endpoint_jsonifier/static/description/icon.png
odoo/addons/endpoint_jsonifier/static/description/index.html
odoo/addons/endpoint_jsonifier/views/endpoint_endpoint.xml
odoo_addon_endpoint_jsonifier-18.0.1.0.0.2.dist-info/METADATA
odoo_addon_endpoint_jsonifier-18.0.1.0.0.2.dist-info/WHEEL
odoo_addon_endpoint_jsonifier-18.0.1.0.0.2.dist-info/top_level.txt
odoo_addon_endpoint_jsonifier-18.0.1.0.0.2.dist-info/RECORD
