Metadata-Version: 2.1
Name: odoo-addon-endpoint_jsonifier
Version: 18.0.1.0.0.2
Requires-Python: >=3.10
Requires-Dist: odoo-addon-endpoint==18.0.*
Requires-Dist: odoo-addon-jsonifier==18.0.*
Requires-Dist: odoo==18.0.*
Summary: Allow to configure jsonifier parsers on endpoints
Home-page: https://github.com/OCA/web-api
License: LGPL-3
Author: Camptocamp, Odoo Community Association (OCA)
Author-email: support@odoo-community.org
Classifier: Programming Language :: Python
Classifier: Framework :: Odoo
Classifier: Framework :: Odoo :: 18.0
Classifier: License :: OSI Approved :: GNU Lesser General Public License v3 (LGPLv3)
